<?xml version='1.0' encoding='ASCII'?>
<ccp4:ccp4i2 xmlns:ccp4="http://www.ccp4.ac.uk/ccp4ns">
  <ccp4i2_header>
    <function>DEF</function>
    <pluginName>xia2_pointless</pluginName>
  </ccp4i2_header>
  <ccp4i2_body id="xia2_pointless">
  <container id="inputData">
    <content id="XIA2_DIRECTORY">
      <className>CDataFile</className>
      <qualifiers>
        <mustExist>True</mustExist>
	<allowUndefined>False</allowUndefined>
	<isDirectory>True</isDirectory>
         <saveToDb>False</saveToDb>
      </qualifiers>
    </content>
  </container>
  <container id="outputData">
    <content id="HKLOUT">
      <className>CMtzDataFile</className>
      <qualifiers>
         <saveToDb>True</saveToDb>
      </qualifiers>
    </content>
  </container>
  <container id="controlParameters">
   </container>
  </ccp4i2_body>
</ccp4:ccp4i2>
